{"title": "comment moderation", "displaytitle": "comment moderation", "thumbnail": {"source": "https://cdn4.wpbeginner.com/wp-content/uploads/2014/09/post-comments-wordpress.png", "width": 320, "height": 154}, "lang": "en", "dir": "ltr", "extract": "Comment moderation is a feature in WordPress that allows you to prevent comments from appearing on your site without your express approval. Moderation can be very useful in addressing Comment Spam, but it has more general applications as well.", "extract_html": "<div aria-level=\"3\" class=\"LGOjhe\" data-hveid=\"CAcQBw\" role=\"heading\"><span class=\"ILfuVd\"><b>Comment moderation</b> is a feature in WordPress that allows you to prevent <b>comments</b> from appearing on your site without your express approval. <b>Moderation</b> can be very useful in addressing <b>Comment</b> Spam, but it has more general applications as well.</span></div>"}