{"title": "industrial control systems", "displaytitle": "industrial control systems", "thumbnail": {"source": "https://upload.wikimedia.org/wikipedia/commons/1/10/Functional_levels_of_a_Distributed_Control_System.svg", "width": 320, "height": 154}, "lang": "en", "dir": "ltr", "extract": "Industrial control system (ICS) is a general term that encompasses several types of control systems and associated instrumentation used for industrial process control.", "extract_html": "<div aria-level=\"3\" class=\"LGOjhe\" data-hveid=\"CAcQBw\" role=\"heading\"><span class=\"ILfuVd\"><b>Industrial control system</b> (ICS) is a general term that encompasses several types of <b>control systems</b> and associated instrumentation used for <b>industrial process control</b>.</span></div>"}