{"title": "malicious email", "displaytitle": "malicious email", "thumbnail": {"source": "https://acsc.gov.au/publications/protect/images/malicious-email-live-link.gif", "width": 320, "height": 154}, "lang": "en", "dir": "ltr", "extract": "Email content filtering performed on the body of an email helps provide a defence-in-depth approach to email content filtering. The possible attack surface presented by the body of an email is less than attachments; however, content in an email body can still introduce malicious content to a network.", "extract_html": "<div aria-level=\"3\" class=\"LGOjhe\" data-hveid=\"CAYQBw\" role=\"heading\"><span class=\"ILfuVd\"><b>Email</b> content filtering performed on the body of an <b>email</b> helps provide a defence-in-depth approach to <b>email</b> content filtering. The possible attack surface presented by the body of an <b>email</b> is less than attachments; however, content in an <b>email</b> body can still introduce <b>malicious</b> content to a network.</span></div>"}