{"title": "market development", "displaytitle": "market development", "thumbnail": {"source": "https://www.ioipartners.com/wp-content/uploads/2016/07/market-development-service.jpg", "width": 320, "height": 154}, "lang": "en", "dir": "ltr", "extract": "Market development is a Know growth strategy that identifies and develops new market segments for current products. A market development strategy targets non-buying customers in currently targeted segments. It also targets new customers in new segments.", "extract_html": "<div aria-level=\"3\" class=\"LGOjhe\" data-hveid=\"CAUQBw\" role=\"heading\"><span class=\"ILfuVd\"><b>Market development</b> is a Know growth strategy that identifies and develops new <b>market</b> segments for current products. A <b>market development</b> strategy targets non-buying customers in currently targeted segments. It also targets new customers in new segments.</span></div>"}