{"title": "Windows operating system", "displaytitle": "Windows operating system", "thumbnail": {"source": "https://www.webopedia.com/imagesvr_ce/626/windows-os-windows-95.jpg", "width": 320, "height": 154}, "lang": "en", "dir": "ltr", "extract": "Windows OS, computer operating system (OS) developed by Microsoft Corporation to run personal computers (PCs). Featuring the first graphical user interface (GUI) for IBM-compatible PCs, the Windows OS soon dominated the PC market.", "extract_html": "<div aria-level=\"3\" class=\"LGOjhe\" data-hveid=\"CAcQBw\" role=\"heading\"><span class=\"ILfuVd\"><b>Windows OS</b>, computer <b>operating system</b> (<b>OS</b>) developed by Microsoft Corporation to run personal computers (PCs). Featuring the first graphical user interface (GUI) for IBM-compatible PCs, the <b>Windows OS</b> soon dominated the PC market.</span></div>"}