{"title": "Business", "displaytitle": "Business", "thumbnail": {"source": "https://upload.wikimedia.org/wikipedia/commons/thumb/5/5b/Society.svg/320px-Society.svg.png", "width": 320, "height": 127}, "lang": "en", "dir": "ltr", "extract": "Business is the activity of making one's living or making money by producing or buying and selling products. Simply put, it is \"any activity or enterprise entered into for profit. It does not mean it is a company, a corporation, partnership, or have any such formal organization, but it can range from a street peddler to General Motors.\"", "extract_html": "<p><b>Business</b> is the activity of making one's living or making money by producing or buying and selling products. Simply put, it is \"any activity or enterprise entered into for profit. It does not mean it is a company, a corporation, partnership, or have any such formal organization, but it can range from a street peddler to General Motors.\"</p>"}