{"title": "CAST-128", "displaytitle": "CAST-128", "thumbnail": {"source": "https://upload.wikimedia.org/wikipedia/commons/thumb/6/6a/CAST-128-large.png/142px-CAST-128-large.png", "width": 142, "height": 320}, "lang": "en", "dir": "ltr", "extract": "In cryptography, CAST-128 is a symmetric-key block cipher used in a number of products, notably as the default cipher in some versions of GPG and PGP. It has also been approved for Government of Canada use by the Communications Security Establishment. The algorithm was created in 1996 by Carlisle Adams and Stafford Tavares using the CAST design procedure.", "extract_html": "<p>In cryptography, <b>CAST-128</b> is a symmetric-key block cipher used in a number of products, notably as the default cipher in some versions of GPG and PGP. It has also been approved for Government of Canada use by the Communications Security Establishment. The algorithm was created in 1996 by Carlisle Adams and Stafford Tavares using the <b>CAST</b> design procedure.</p>"}