{"title": "Kaspersky Lab", "displaytitle": "Kaspersky Lab", "thumbnail": {"source": "https://upload.wikimedia.org/wikipedia/commons/thumb/e/ea/Kaspersky_virlab.JPG/320px-Kaspersky_virlab.JPG", "width": 320, "height": 213}, "lang": "en", "dir": "ltr", "extract": "Kaspersky Lab is a multinational cybersecurity and anti-virus provider headquartered in Moscow, Russia and operated by a holding company in the United Kingdom. It was founded in 1997 by Eugene Kaspersky, Natalya Kaspersky, and Alexey De-Monderik; Eugene Kaspersky is currently the CEO. Kaspersky Lab develops and sells antivirus, internet security, password management, endpoint security, and other cybersecurity products and services.", "extract_html": "<p><b>Kaspersky Lab</b> is a multinational cybersecurity and anti-virus provider headquartered in Moscow, Russia and operated by a holding company in the United Kingdom. It was founded in 1997 by Eugene Kaspersky, Natalya Kaspersky, and Alexey De-Monderik; Eugene Kaspersky is currently the CEO. Kaspersky Lab develops and sells antivirus, internet security, password management, endpoint security, and other cybersecurity products and services.</p>"}