{"title": "Reuters", "displaytitle": "Reuters", "thumbnail": {"source": "https://upload.wikimedia.org/wikipedia/commons/thumb/9/9c/Reuters-Building-30SC.JPG/320px-Reuters-Building-30SC.JPG", "width": 320, "height": 257}, "lang": "en", "dir": "ltr", "extract": "Reuters is an international news organization. It is a division of Thomson Reuters and has nearly 200 locations around the world. Until 2008, the Reuters news agency formed part of an independent company, Reuters Group plc, which was also a provider of financial market data. Since the acquisition of Reuters Group by the Thomson Corporation in 2008, the Reuters news agency has been a part of Thomson Reuters, making up the media division. Reuters transmits news in English, French, German, Italian, Spanish, Portuguese, Russian, Urdu, Arabic, Japanese, Korean, and Chinese. It was established in 1851.", "extract_html": "<p><b>Reuters</b> is an international news organization headquartered in London, United Kingdom.. It is a division of Thomson Reuters and has nearly 200 locations around the world. Until 2008, the Reuters news agency formed part of an independent company, Reuters Group plc, which was also a provider of financial market data. Since the acquisition of Reuters Group by the Thomson Corporation in 2008, the Reuters news agency has been a part of Thomson Reuters, making up the media division. Reuters transmits news in English, French, German, Italian, Spanish, Portuguese, Russian, Urdu, Arabic, Japanese, Korean, and Chinese. It was established in 1851.</p>"}