{"title": "Targets", "displaytitle": "<i>Targets</i>", "thumbnail": {"source": "https://upload.wikimedia.org/wikipedia/en/thumb/6/63/Targetsposter.jpg/215px-Targetsposter.jpg", "width": 215, "height": 320}, "lang": "en", "dir": "ltr", "extract": "Targets is a 1968 American neo-noir thriller, written and directed by Peter Bogdanovich and filmed in color by L\u00e1szl\u00f3 Kov\u00e1cs.", "extract_html": "<p><i><b>Targets</b></i> is a 1968 American neo-noir thriller, written and directed by Peter Bogdanovich and filmed in color by L\u00c3\u00a1szl\u00c3\u00b3 Kov\u00c3\u00a1cs.</p>"}