{"title": "6K qubits", "displaytitle": "6K qubits", "thumbnail": {"source": "https://ktd4869.github.io/Tool/figure/default.jpg", "width": 320, "height": 154}, "lang": "en", "dir": "ltr", "extract": "A pure qubit state is a coherent superposition of the basis states. This means that a single qubit can be described by a linear combination of.", "extract_html": "<div aria-level=\"3\" class=\"LGOjhe\" data-hveid=\"CAYQAQ\" role=\"heading\"><span class=\"ILfuVd\">A pure <b>qubit</b> state is a coherent superposition of the basis states. This means that a single <b>qubit</b> can be described by a linear combination of.</span></div>"}