{"title": "Apple iCloud", "displaytitle": "Apple iCloud", "thumbnail": {"source": "https://ktd4869.github.io/Tool/figure/default.jpg", "width": 320, "height": 154}, "lang": "en", "dir": "ltr", "extract": "iCloud is a suite of free cloud-based services from Apple that helps users store and synchronize digital content across computers and numerous iOS-supported devices such as the iPhone, iPad or iPod Touch.", "extract_html": "<div aria-level=\"3\" class=\"LGOjhe\" data-hveid=\"CAYQAQ\" role=\"heading\"><span class=\"ILfuVd\"><b>iCloud</b> is a suite of free cloud-based services from <b>Apple</b> that helps users store and synchronize digital content across computers and numerous iOS-supported devices such as the iPhone, iPad or iPod Touch.</span></div>"}