{"title": "Cloud service providers supply", "displaytitle": "Cloud service providers supply", "thumbnail": {"source": "https://ktd4869.github.io/Tool/figure/default.jpg", "width": 320, "height": 154}, "lang": "en", "dir": "ltr", "extract": "A cloud service is any service made available to users on demand via the Internet from a cloud computing provider's servers as opposed to being provided from a company's own on-premises servers.", "extract_html": "<div aria-level=\"3\" class=\"LGOjhe\" data-hveid=\"CAcQAQ\" role=\"heading\"><span class=\"ILfuVd\">A <b>cloud service</b> is any <b>service</b> made available to users on demand via the <b>Internet</b> from a <b>cloud computing provider's</b> servers as opposed to being provided from a company's own on-premises servers.</span></div>"}