{"title": "cryptographic binding", "displaytitle": "cryptographic binding", "thumbnail": {"source": "https://ktd4869.github.io/Tool/figure/default.jpg", "width": 320, "height": 154}, "lang": "en", "dir": "ltr", "extract": "Definition(s): Associating two or more related elements of information using cryptographic techniques. ... Cryptographic binding works by determining the hash value of each object attribute associated with a specific object and digitally signing the collection of hashed values.", "extract_html": "<div aria-level=\"3\" class=\"LGOjhe\" data-hveid=\"CAEQAQ\" role=\"heading\"><span class=\"ILfuVd\"><b>Definition</b>(s): Associating two or more related elements of information using <b>cryptographic</b> techniques. ... <b>Cryptographic binding</b> works by determining the hash value of each object attribute associated with a specific object and digitally signing the collection of hashed values.</span></div>"}