{"title": "Javapowered", "displaytitle": "Javapowered", "thumbnail": {"source": "https://ktd4869.github.io/Tool/figure/default.jpg", "width": 320, "height": 154}, "lang": "en", "dir": "ltr", "extract": "noun. mass noun. 1The state of being connected or interconnected. 'the authorities worked at restoring connectivity between Puerto Rico and the US mainland after Hurricane Hugo' 'Going by their current strengths, these libraries will survive the age of seamless connectivity too.'", "extract_html": "<div aria-level=\"3\" class=\"LGOjhe\" data-hveid=\"CAkQAQ\" role=\"heading\"><span class=\"ILfuVd\">noun. mass noun. 1The state of being connected or interconnected. 'the authorities worked at restoring connectivity between Puerto Rico and the US mainland after Hurricane Hugo' 'Going by their current strengths, these libraries will survive the age of seamless connectivity too.'</span></div>"}