{"title": "magnetic field frequencies", "displaytitle": "magnetic field frequencies", "thumbnail": {"source": "https://ktd4869.github.io/Tool/figure/default.jpg", "width": 320, "height": 154}, "lang": "en", "dir": "ltr", "extract": "Other technologies produce intermediate frequency (IF) fields with frequencies from 300 Hz to 10 MHz and radiofrequency (RF) fields with frequencies of 10 MHz to 300 GHz. The effects of electromagnetic fields on the human body depend not only on their field level but on their frequency and energy.", "extract_html": "<div aria-level=\"3\" class=\"LGOjhe\" data-hveid=\"CAEQAQ\" role=\"heading\"><span class=\"ILfuVd\">Other technologies produce intermediate <b>frequency</b> (IF) <b>fields</b> with <b>frequencies</b> from 300 Hz to 10 MHz and radiofrequency (RF) <b>fields</b> with <b>frequencies</b> of 10 MHz to 300 GHz. The effects of electromagnetic <b>fields</b> on the human body depend not only on their <b>field</b> level but on their <b>frequency</b> and energy.</span></div>"}