{"title": "regulatory requirements", "displaytitle": "regulatory requirements", "thumbnail": {"source": "https://ktd4869.github.io/Tool/figure/default.jpg", "width": 320, "height": 154}, "lang": "en", "dir": "ltr", "extract": "In general, compliance means conforming to a rule, such as a specification, policy, standard or law. Regulatory compliance describes the goal that organizations aspire to achieve in their efforts to ensure that they are aware of and take steps to comply with relevant laws, policies, and regulations.", "extract_html": "<div aria-level=\"3\" class=\"LGOjhe\" data-hveid=\"CAYQAQ\" role=\"heading\"><span class=\"ILfuVd\">In general, <b>compliance</b> means conforming to a rule, such as a specification, policy, standard or law. <b>Regulatory compliance</b> describes the goal that organizations aspire to achieve in their efforts to ensure that they are aware of and take steps to comply with relevant laws, policies, and <b>regulations</b>.</span></div>"}