{"title": "security strategy", "displaytitle": "security strategy", "thumbnail": {"source": "https://ktd4869.github.io/Tool/figure/default.jpg", "width": 320, "height": 154}, "lang": "en", "dir": "ltr", "extract": "A security strategy is thus an important document which details out series of steps necessary for an organization to identify, remediate and manage risks while staying complaint. An effective security strategy is comprehensive and dynamic, with the elasticity to respond to any type of security threat.", "extract_html": "<div aria-level=\"3\" class=\"LGOjhe\" data-hveid=\"CAcQAQ\" role=\"heading\"><span class=\"ILfuVd\">A <b>security strategy</b> is thus an important document which details out series of steps necessary for an organization to identify, remediate and manage risks while staying complaint. An effective <b>security strategy</b> is comprehensive and dynamic, with the elasticity to respond to any type of <b>security</b> threat.</span></div>"}