{"title": "magnetic fields emanating", "displaytitle": "magnetic fields emanating", "thumbnail": {"source": "https://ktd4869.github.io/Tool/figure/default.jpg", "width": 320, "height": 154}, "lang": "en", "dir": "ltr", "extract": "A model of an object that generates a magnetic field in which the field is considered to emanate from two opposite poles, as in the north and south poles of a magnet, much as an electric field emanates from a positive and a negative charge (each of which is a monopole ) in an electric dipole.", "extract_html": "<div aria-level=\"3\" class=\"LGOjhe\" data-hveid=\"CAoQAQ\" role=\"heading\"><span class=\"ILfuVd\">A model of an object that generates a <b>magnetic field</b> in which the <b>field</b> is considered to <b>emanate</b> from two opposite poles, as in the north and south poles of a <b>magnet</b>, much as an electric <b>field emanates</b> from a positive and a negative charge (each of which is a monopole ) in an electric dipole.</span></div>"}