{"title": "PS command to", "displaytitle": "PS command to", "thumbnail": {"source": "https://ktd4869.github.io/Tool/figure/default.jpg", "width": 320, "height": 154}, "lang": "en", "dir": "ltr", "extract": "The ps Command. The ps (i.e., process status) command is used to provide information about the currently running processes, including their process identification numbers (PIDs). A process, also referred to as a task, is an executing (i.e., running) instance of a program.May 20, 2005", "extract_html": "<div aria-level=\"3\" class=\"LGOjhe\" data-hveid=\"CAYQAQ\" role=\"heading\"><span class=\"ILfuVd\">The <b>ps Command</b>. The <b>ps</b> (i.e., process status) <b>command</b> is used to provide information about the currently running processes, including their process identification numbers (PIDs). A process, also referred to as a task, is an executing (i.e., running) instance of a program.</span><span class=\"kX21rb\">May 20, 2005</span></div>"}