{"title": "T5 Portable drives", "displaytitle": "T5 Portable drives", "thumbnail": {"source": "https://ktd4869.github.io/Tool/figure/default.jpg", "width": 320, "height": 154}, "lang": "en", "dir": "ltr", "extract": "Portable hard drives are the answer and the Samsung Portable SSD T5 is the big daddy of them all. ... For a modern USB-C capable device you're going to get huge transfer speeds \u2013 up to 540MB/s, meaning you can drag and drop your files, and even work directly from the portable external disk.Jan 22, 2018", "extract_html": "<div aria-level=\"3\" class=\"LGOjhe\" data-hveid=\"CAcQAQ\" role=\"heading\"><span class=\"ILfuVd\"><b>Portable</b> hard <b>drives</b> are the answer and the Samsung <b>Portable</b> SSD <b>T5</b> is the big daddy of them all. ... For a modern USB-C capable device you're going to get huge transfer speeds \u2013 up to 540MB/s, <b>meaning</b> you can drag and drop your files, and even work directly from the <b>portable</b> external <b>disk</b>.</span><span class=\"kX21rb\">Jan 22, 2018</span></div>"}