{"title": "technical counterintelligence investigations", "displaytitle": "technical counterintelligence investigations", "thumbnail": {"source": "https://ktd4869.github.io/Tool/figure/default.jpg", "width": 320, "height": 154}, "lang": "en", "dir": "ltr", "extract": "Counterintelligence (CI) investigations are conducted to prove or disprove an allegation of espionage or otherintelligence activities, such as sabotage, assassination, or other national security crimes conducted by or on behalf of aforeign government, organization, or person or international terrorists.", "extract_html": "<div aria-level=\"3\" class=\"LGOjhe\" data-hveid=\"CAcQAQ\" role=\"heading\"><span class=\"ILfuVd\"><b>Counterintelligence</b> (CI) <b>investigations</b> are conducted to prove or disprove an allegation of espionage or otherintelligence activities, such as sabotage, assassination, or other national security crimes conducted by or on behalf of aforeign government, organization, or person or international terrorists.</span></div>"}